{
	"$schema": "http://schema.management.azure.com/schemas/2015-01-01/deploymentTemplate.json#",
	"contentVersion": "1.0.0.0",
	"parameters": {
		"factoryName": {
			"type": "string",
			"metadata": "Data Factory name",
			"defaultValue": "adfaditya"
		},
		"AzureBlobStorage1_connectionString": {
			"type": "secureString",
			"metadata": "Secure string for 'connectionString' of 'AzureBlobStorage1'"
		},
		"AzureBlobStorageoutLS_connectionString": {
			"type": "secureString",
			"metadata": "Secure string for 'connectionString' of 'AzureBlobStorageoutLS'"
		},
		"AzureDataLakeStorage1_accountKey": {
			"type": "secureString",
			"metadata": "Secure string for 'accountKey' of 'AzureDataLakeStorage1'"
		},
		"AzureSqlDatabase1_connectionString": {
			"type": "secureString",
			"metadata": "Secure string for 'connectionString' of 'AzureSqlDatabase1'"
		},
		"AzureSqlDatabase2_connectionString": {
			"type": "secureString",
			"metadata": "Secure string for 'connectionString' of 'AzureSqlDatabase2'"
		},
		"AzureSqlDatabase3_connectionString": {
			"type": "secureString",
			"metadata": "Secure string for 'connectionString' of 'AzureSqlDatabase3'"
		},
		"AzureSqlDatabase4_connectionString": {
			"type": "secureString",
			"metadata": "Secure string for 'connectionString' of 'AzureSqlDatabase4'"
		},
		"AzureSqlDatabase5_connectionString": {
			"type": "secureString",
			"metadata": "Secure string for 'connectionString' of 'AzureSqlDatabase5'"
		},
		"AzureSqlDatabase6_connectionString": {
			"type": "secureString",
			"metadata": "Secure string for 'connectionString' of 'AzureSqlDatabase6'"
		},
		"AzureSqlDatabase7_connectionString": {
			"type": "secureString",
			"metadata": "Secure string for 'connectionString' of 'AzureSqlDatabase7'"
		},
		"AzureSqlmydbLS_connectionString": {
			"type": "secureString",
			"metadata": "Secure string for 'connectionString' of 'AzureSqlmydbLS'"
		},
		"DestinationProductDBLS_connectionString": {
			"type": "secureString",
			"metadata": "Secure string for 'connectionString' of 'DestinationProductDBLS'"
		},
		"DimProductSourceLS_connectionString": {
			"type": "secureString",
			"metadata": "Secure string for 'connectionString' of 'DimProductSourceLS'"
		},
		"ProductSourceLS_connectionString": {
			"type": "secureString",
			"metadata": "Secure string for 'connectionString' of 'ProductSourceLS'"
		},
		"SqlSampleDBLS_connectionString": {
			"type": "secureString",
			"metadata": "Secure string for 'connectionString' of 'SqlSampleDBLS'"
		},
		"SqlServer1_connectionString": {
			"type": "secureString",
			"metadata": "Secure string for 'connectionString' of 'SqlServer1'"
		},
		"SqlServer1_password": {
			"type": "secureString",
			"metadata": "Secure string for 'password' of 'SqlServer1'"
		},
		"SqlServer2_connectionString": {
			"type": "secureString",
			"metadata": "Secure string for 'connectionString' of 'SqlServer2'"
		},
		"SqlServer2_password": {
			"type": "secureString",
			"metadata": "Secure string for 'password' of 'SqlServer2'"
		},
		"SqlServer3_connectionString": {
			"type": "secureString",
			"metadata": "Secure string for 'connectionString' of 'SqlServer3'"
		},
		"SqlServer4_connectionString": {
			"type": "secureString",
			"metadata": "Secure string for 'connectionString' of 'SqlServer4'"
		},
		"SqlServer4_password": {
			"type": "secureString",
			"metadata": "Secure string for 'password' of 'SqlServer4'"
		},
		"SqlServerq1_connectionString": {
			"type": "secureString",
			"metadata": "Secure string for 'connectionString' of 'SqlServerq1'"
		},
		"SqlServerq1_password": {
			"type": "secureString",
			"metadata": "Secure string for 'password' of 'SqlServerq1'"
		},
		"q3sqlsource_connectionString": {
			"type": "secureString",
			"metadata": "Secure string for 'connectionString' of 'q3sqlsource'"
		},
		"q4sourceserver_connectionString": {
			"type": "secureString",
			"metadata": "Secure string for 'connectionString' of 'q4sourceserver'"
		},
		"q4sourceserver_password": {
			"type": "secureString",
			"metadata": "Secure string for 'password' of 'q4sourceserver'"
		},
		"q5sourcels_connectionString": {
			"type": "secureString",
			"metadata": "Secure string for 'connectionString' of 'q5sourcels'"
		},
		"AzureDataLakeStorage1_properties_typeProperties_url": {
			"type": "string",
			"defaultValue": "https://strgacctgen2.dfs.core.windows.net"
		},
		"SqlServer1_properties_typeProperties_userName": {
			"type": "string",
			"defaultValue": "ADITYA\\adity"
		},
		"SqlServer2_properties_typeProperties_userName": {
			"type": "string",
			"defaultValue": "ADITYA\\adity"
		},
		"SqlServer3_properties_typeProperties_userName": {
			"type": "string",
			"defaultValue": "@{linkedService().USERNAME}"
		},
		"SqlServer4_properties_typeProperties_userName": {
			"type": "string",
			"defaultValue": "adity"
		},
		"SqlServerq1_properties_typeProperties_userName": {
			"type": "string",
			"defaultValue": "adity"
		},
		"q4sourceserver_properties_typeProperties_userName": {
			"type": "string",
			"defaultValue": "adity"
		},
		"containerUri": {
			"type": "string",
			"metadata": "URI to storage account containing linked ARM templates"
		},
		"containerSasToken": {
			"type": "string",
			"metadata": "Sas token to storage account containing linked ARM templates"
		}
	},
	"variables": {
		"factoryId": "[concat('Microsoft.DataFactory/factories/', parameters('factoryName'))]"
	},
	"resources": [
		{
			"name": "adfaditya_ArmTemplate_0",
			"type": "Microsoft.Resources/deployments",
			"apiVersion": "2018-02-01",
			"properties": {
				"mode": "incremental",
				"templateLink": {
					"uri": "[concat(parameters('containerUri'), '/ArmTemplate_0.json', parameters('containerSasToken'))]",
					"contentVersion": "1.0.0.0"
				},
				"parameters": {
					"factoryName": {
						"value": "[parameters('factoryName')]"
					},
					"AzureBlobStorage1_connectionString": {
						"value": "[parameters('AzureBlobStorage1_connectionString')]"
					},
					"AzureBlobStorageoutLS_connectionString": {
						"value": "[parameters('AzureBlobStorageoutLS_connectionString')]"
					},
					"AzureDataLakeStorage1_accountKey": {
						"value": "[parameters('AzureDataLakeStorage1_accountKey')]"
					},
					"AzureSqlDatabase1_connectionString": {
						"value": "[parameters('AzureSqlDatabase1_connectionString')]"
					},
					"AzureSqlDatabase2_connectionString": {
						"value": "[parameters('AzureSqlDatabase2_connectionString')]"
					},
					"AzureSqlDatabase3_connectionString": {
						"value": "[parameters('AzureSqlDatabase3_connectionString')]"
					},
					"AzureSqlDatabase4_connectionString": {
						"value": "[parameters('AzureSqlDatabase4_connectionString')]"
					},
					"AzureSqlDatabase5_connectionString": {
						"value": "[parameters('AzureSqlDatabase5_connectionString')]"
					},
					"AzureSqlDatabase6_connectionString": {
						"value": "[parameters('AzureSqlDatabase6_connectionString')]"
					},
					"AzureSqlDatabase7_connectionString": {
						"value": "[parameters('AzureSqlDatabase7_connectionString')]"
					},
					"AzureSqlmydbLS_connectionString": {
						"value": "[parameters('AzureSqlmydbLS_connectionString')]"
					},
					"DestinationProductDBLS_connectionString": {
						"value": "[parameters('DestinationProductDBLS_connectionString')]"
					},
					"DimProductSourceLS_connectionString": {
						"value": "[parameters('DimProductSourceLS_connectionString')]"
					},
					"ProductSourceLS_connectionString": {
						"value": "[parameters('ProductSourceLS_connectionString')]"
					},
					"SqlSampleDBLS_connectionString": {
						"value": "[parameters('SqlSampleDBLS_connectionString')]"
					},
					"SqlServer1_connectionString": {
						"value": "[parameters('SqlServer1_connectionString')]"
					},
					"SqlServer1_password": {
						"value": "[parameters('SqlServer1_password')]"
					},
					"SqlServer2_connectionString": {
						"value": "[parameters('SqlServer2_connectionString')]"
					},
					"SqlServer2_password": {
						"value": "[parameters('SqlServer2_password')]"
					},
					"q3sqlsource_connectionString": {
						"value": "[parameters('q3sqlsource_connectionString')]"
					},
					"q5sourcels_connectionString": {
						"value": "[parameters('q5sourcels_connectionString')]"
					},
					"AzureDataLakeStorage1_properties_typeProperties_url": {
						"value": "[parameters('AzureDataLakeStorage1_properties_typeProperties_url')]"
					},
					"SqlServer1_properties_typeProperties_userName": {
						"value": "[parameters('SqlServer1_properties_typeProperties_userName')]"
					},
					"SqlServer2_properties_typeProperties_userName": {
						"value": "[parameters('SqlServer2_properties_typeProperties_userName')]"
					}
				}
			},
			"dependsOn": []
		},
		{
			"name": "adfaditya_ArmTemplate_1",
			"type": "Microsoft.Resources/deployments",
			"apiVersion": "2018-02-01",
			"properties": {
				"mode": "incremental",
				"templateLink": {
					"uri": "[concat(parameters('containerUri'), '/ArmTemplate_1.json', parameters('containerSasToken'))]",
					"contentVersion": "1.0.0.0"
				},
				"parameters": {
					"factoryName": {
						"value": "[parameters('factoryName')]"
					}
				}
			},
			"dependsOn": [
				"[resourceId('Microsoft.Resources/deployments', 'adfaditya_ArmTemplate_0')]"
			]
		},
		{
			"name": "adfaditya_ArmTemplate_2",
			"type": "Microsoft.Resources/deployments",
			"apiVersion": "2018-02-01",
			"properties": {
				"mode": "incremental",
				"templateLink": {
					"uri": "[concat(parameters('containerUri'), '/ArmTemplate_2.json', parameters('containerSasToken'))]",
					"contentVersion": "1.0.0.0"
				},
				"parameters": {
					"factoryName": {
						"value": "[parameters('factoryName')]"
					},
					"SqlServer3_connectionString": {
						"value": "[parameters('SqlServer3_connectionString')]"
					},
					"SqlServer4_connectionString": {
						"value": "[parameters('SqlServer4_connectionString')]"
					},
					"SqlServer4_password": {
						"value": "[parameters('SqlServer4_password')]"
					},
					"SqlServerq1_connectionString": {
						"value": "[parameters('SqlServerq1_connectionString')]"
					},
					"SqlServerq1_password": {
						"value": "[parameters('SqlServerq1_password')]"
					},
					"q4sourceserver_connectionString": {
						"value": "[parameters('q4sourceserver_connectionString')]"
					},
					"q4sourceserver_password": {
						"value": "[parameters('q4sourceserver_password')]"
					},
					"SqlServer3_properties_typeProperties_userName": {
						"value": "[parameters('SqlServer3_properties_typeProperties_userName')]"
					},
					"SqlServer4_properties_typeProperties_userName": {
						"value": "[parameters('SqlServer4_properties_typeProperties_userName')]"
					},
					"SqlServerq1_properties_typeProperties_userName": {
						"value": "[parameters('SqlServerq1_properties_typeProperties_userName')]"
					},
					"q4sourceserver_properties_typeProperties_userName": {
						"value": "[parameters('q4sourceserver_properties_typeProperties_userName')]"
					}
				}
			},
			"dependsOn": [
				"[resourceId('Microsoft.Resources/deployments', 'adfaditya_ArmTemplate_1')]"
			]
		}
	]
}